setup.cfg
setup.py
doze/__init__.py
doze/tests.py
doze.egg-info/PKG-INFO
doze.egg-info/SOURCES.txt
doze.egg-info/dependency_links.txt
doze.egg-info/entry_points.txt
doze.egg-info/top_level.txt
doze.egg-info/zip-safe