Metadata-Version: 1.0
Name: doze
Version: 0.1
Summary: Lazy URL construction
Home-page: https://github.com/ericmoritz/doze
Author: Eric Moritz
Author-email: eric@themoritzfamily.com
License: BSD
Platform: UNKNOWN
Classifier: Development Status :: 3 - Alpha
Classifier: Intended Audience :: Developers
Classifier: License :: OSI Approved :: BSD License
